phisaver_client/.gitignore
phisaver_client/README.md
phisaver_client/__init__.py
phisaver_client/client.py
phisaver_client/errors.py
phisaver_client/helpers.py
phisaver_client/py.typed
phisaver_client/pyproject.toml
phisaver_client/types.py
phisaver_client/api/__init__.py
phisaver_client/api/devices/__init__.py
phisaver_client/api/devices/devices_create.py
phisaver_client/api/devices/devices_destroy.py
phisaver_client/api/devices/devices_list.py
phisaver_client/api/devices/devices_partial_update.py
phisaver_client/api/devices/devices_retrieve.py
phisaver_client/api/devices/devices_update.py
phisaver_client/api/fleets/__init__.py
phisaver_client/api/fleets/fleets_colours_retrieve.py
phisaver_client/api/fleets/fleets_create.py
phisaver_client/api/fleets/fleets_destroy.py
phisaver_client/api/fleets/fleets_list.py
phisaver_client/api/fleets/fleets_partial_update.py
phisaver_client/api/fleets/fleets_retrieve.py
phisaver_client/api/fleets/fleets_update.py
phisaver_client/api/login/__init__.py
phisaver_client/api/login/login_create.py
phisaver_client/api/logout/__init__.py
phisaver_client/api/logout/logout_create.py
phisaver_client/api/password/__init__.py
phisaver_client/api/password/password_change_create.py
phisaver_client/api/password/password_reset_confirm_create.py
phisaver_client/api/password/password_reset_create.py
phisaver_client/api/token/__init__.py
phisaver_client/api/token/token_create.py
phisaver_client/api/ts/__init__.py
phisaver_client/api/ts/ts_heatmap_retrieve.py
phisaver_client/api/ts/ts_metrics_retrieve.py
phisaver_client/api/ts/ts_series_retrieve.py
phisaver_client/api/ts/ts_table_retrieve.py
phisaver_client/api/user/__init__.py
phisaver_client/api/user/user_partial_update.py
phisaver_client/api/user/user_retrieve.py
phisaver_client/api/user/user_update.py
phisaver_client/api/users/__init__.py
phisaver_client/api/users/users_claim_partial_update.py
phisaver_client/api/users/users_create.py
phisaver_client/api/users/users_current_retrieve.py
phisaver_client-1.0.4.dist-info/METADATA
phisaver_client-1.0.4.dist-info/WHEEL
phisaver_client-1.0.4.dist-info/licenses/LICENSE
phisaver_client-1.0.4.dist-info/RECORD
